{"children":[{"name":"module-info.java","size":21},{"name":"com","children":[{"name":"telenav","children":[{"name":"kivakit","children":[{"name":"commandline","children":[{"name":"ApplicationMetadata.java","size":99},{"name":"ArgumentParser.java","size":897},{"name":"ArgumentParsers.java","size":191},{"name":"ArgumentValue.java","size":184},{"name":"ArgumentValueList.java","size":303},{"name":"CommandLine.java","size":851},{"name":"CommandLineParser.java","size":813},{"name":"Quantifier.java","size":92},{"name":"SwitchParser.java","size":1251},{"name":"SwitchParsers.java","size":716},{"name":"SwitchValue.java","size":169},{"name":"SwitchValueList.java","size":284},{"name":"internal","children":[{"name":"lexakai","children":[{"name":"DiagramArgument.java","size":36},{"name":"DiagramCommandLine.java","size":36},{"name":"DiagramSwitch.java","size":36},{"name":"DiagramValidation.java","size":36}]}]},{"name":"parsing","children":[{"name":"ArgumentParserList.java","size":266},{"name":"ArgumentValueListValidator.java","size":178},{"name":"SwitchParserList.java","size":210},{"name":"SwitchValueListValidator.java","size":178}]}]}]}]}]}]}
