{"children":[{"name":"com","children":[{"name":"telenav","children":[{"name":"kivakit","children":[{"name":"settings","children":[{"name":"stores","children":[{"name":"zookeeper","children":[{"name":"ZookeeperChangeListener.java","size":46},{"name":"ZookeeperConnection.java","size":500},{"name":"ZookeeperConnectionListener.java","size":16},{"name":"ZookeeperSettingsStore.java","size":659},{"name":"converters","children":[{"name":"CreateModeConverter.java","size":16}]}]}]}]}]}]}]},{"name":"module-info.java","size":15}],"name":"root"}